{
  "main": {
    "id": "4d1f73b80d90ad80",
    "type": "split",
    "children": [
      {
        "id": "b996bb02065ae61f",
        "type": "tabs",
        "children": [
          {
            "id": "4d99e58c42013b5c",
            "type": "leaf",
            "state": {
              "type": "markdown",
              "state": {
                "file": "Magistrale/Foundations of artificial intelligence/02 - Heuristic search.md",
                "mode": "source",
                "source": false
              },
              "icon": "lucide-file",
              "title": "02 - Heuristic search"
            }
          }
        ]
      }
    ],
    "direction": "vertical"
  },
  "left": {
    "id": "1e520070f8dc2cd6",
    "type": "split",
    "children": [
      {
        "id": "c2d40dac112b69da",
        "type": "tabs",
        "children": [
          {
            "id": "a1163d9af64d6878",
            "type": "leaf",
            "state": {
              "type": "file-explorer",
              "state": {
                "sortOrder": "byCreatedTimeReverse",
                "autoReveal": false
              },
              "icon": "lucide-folder-closed",
              "title": "Files"
            }
          },
          {
            "id": "451b3be92f0d1b8e",
            "type": "leaf",
            "state": {
              "type": "search",
              "state": {
                "query": "",
                "matchingCase": false,
                "explainSearch": false,
                "collapseAll": false,
                "extraContext": false,
                "sortOrder": "alphabetical"
              },
              "icon": "lucide-search",
              "title": "Search"
            }
          },
          {
            "id": "af2867719307eb02",
            "type": "leaf",
            "state": {
              "type": "bookmarks",
              "state": {},
              "icon": "lucide-bookmark",
              "title": "Bookmarks"
            }
          }
        ]
      }
    ],
    "direction": "horizontal",
    "width": 350.5124969482422
  },
  "right": {
    "id": "282a9548711da6a0",
    "type": "split",
    "children": [
      {
        "id": "55fe9452c7b84ec4",
        "type": "tabs",
        "children": [
          {
            "id": "07e5761cd0257543",
            "type": "leaf",
            "state": {
              "type": "backlink",
              "state": {
                "collapseAll": false,
                "extraContext": false,
                "sortOrder": "alphabetical",
                "showSearch": false,
                "searchQuery": "",
                "backlinkCollapsed": false,
                "unlinkedCollapsed": true
              },
              "icon": "links-coming-in",
              "title": "Backlinks"
            }
          },
          {
            "id": "8f262aef35434a43",
            "type": "leaf",
            "state": {
              "type": "outgoing-link",
              "state": {
                "file": "Terzo anno/Data and web mining/Ensemble methods.md",
                "linksCollapsed": false,
                "unlinkedCollapsed": true
              },
              "icon": "links-going-out",
              "title": "Outgoing links from Ensemble methods"
            }
          },
          {
            "id": "6747196a6c17b1d2",
            "type": "leaf",
            "state": {
              "type": "tag",
              "state": {
                "sortOrder": "frequency",
                "useHierarchy": true
              },
              "icon": "lucide-tags",
              "title": "Tags"
            }
          },
          {
            "id": "92219e5c42d85950",
            "type": "leaf",
            "state": {
              "type": "outline",
              "state": {
                "file": "Terzo anno/Data and web mining/Ensemble methods.md"
              },
              "icon": "lucide-list",
              "title": "Outline of Ensemble methods"
            }
          }
        ]
      }
    ],
    "direction": "horizontal",
    "width": 300,
    "collapsed": true
  },
  "left-ribbon": {
    "hiddenItems": {
      "bases:Create new base": false,
      "switcher:Open quick switcher": true,
      "graph:Open graph view": false,
      "canvas:Create new canvas": true,
      "command-palette:Open command palette": true,
      "obsidian-excalidraw-plugin:New drawing": false
    }
  },
  "active": "4d99e58c42013b5c",
  "lastOpenFiles": [
    "Magistrale/Foundations of artificial intelligence/01 - Blind search.md",
    "Magistrale/Foundations of artificial intelligence/02 - Heuristic search.md",
    "Triennale/Secondo anno/Algoritmi e strutture dati/Mod. 1/Grafi/Connettività e aciclicità.md",
    "Triennale/Terzo anno/Ricerca operativa/Branch & Bound.md",
    "Triennale/Secondo anno/Algoritmi e strutture dati/Mod. 1/Cammini minimi/Introduzione.md",
    "Magistrale/Foundations of artificial intelligence/Images/A star search.svg",
    "Excalidraw/Drawing 2025-10-06 19.10.44.excalidraw.md",
    "Magistrale/Foundations of artificial intelligence/Images/Best first search loop.svg",
    "Triennale/Terzo anno/Calcolabilità e linguaggi formali/Images/Albero di computazione.svg",
    "Excalidraw",
    "Triennale/Secondo anno/Basi di dati/Mod. 1/Introduzione.md",
    "Magistrale/Foundations of artificial intelligence/00 - Introduction.md",
    "Magistrale/Advanced data management/00 - Introduction.md",
    "Triennale/Secondo anno/Basi di dati/Mod. 1/Linguaggi relazionali.md",
    "Nuovo Text Document.txt",
    "Triennale/Secondo anno/Algoritmi e strutture dati/Mod. 2/Alberi/Cos'è un albero.md",
    "Triennale/Secondo anno/Algoritmi e strutture dati/Mod. 2/Alberi/Visite.md",
    "Magistrale/Foundations of artificial intelligence/Images",
    "Magistrale/Foundations of artificial intelligence/Images/Average nodes to explore BFS.png",
    "Calcolo 1/Images",
    "Calcolo 1",
    "Untitled.base",
    "Triennale/Secondo anno/Algoritmi e strutture dati/Mod. 2/Alberi/Alberi binari di ricerca.md",
    "Triennale/Secondo anno/Algoritmi e strutture dati/Mod. 1/Alberi/Minimum Spanning Tree.md",
    "Triennale/Secondo anno/Algoritmi e strutture dati/Mod. 1/Alberi/Generic-MST.md",
    "Triennale/Secondo anno/Algoritmi e strutture dati/Mod. 1/Alberi/Kruskal.md",
    "Triennale/Secondo anno/Algoritmi e strutture dati/Mod. 1/Grafi/Matrici.md",
    "Triennale/Terzo anno/Data and web mining/Reti neurali/Introduzione.md",
    "Triennale/Terzo anno/Data and web mining/Reti neurali/Layers.md",
    "Triennale/Terzo anno/Data and web mining/Regressione lineare.md",
    "Magistrale/Foundations of artificial intelligence",
    "Triennale/Secondo anno/Basi di dati/Mod. 2/Amministrazione/Indici e viste materializzate.md",
    "dbms.md",
    "Magistrale/Advanced data management",
    "Triennale/Primo anno/Secondo semestre/Architettura degli elaboratori mod. 2/ARM ISA/Istruzioni logico-aritmetiche.md",
    "Triennale/Primo anno/Secondo semestre/Architettura degli elaboratori mod. 2/ARM ISA/Branches.md",
    "Master/sd.md",
    "Magistrale",
    "Untitled.md",
    "Master",
    "Calcolo 1/Images/Pasted image 20250522122239.png",
    "Calcolo 1/Images/Pasted image 20250522120450.png",
    "Calcolo 1/Images/Pasted Image 20250428212703_101.jpg",
    "Triennale/Terzo anno/Amministrazione di sistema/Images/Apache core.png",
    "Triennale/Terzo anno/Amministrazione di sistema/Images/Flusso di posta.png",
    "asdasdasd.canvas"
  ]
}